<DOMSymbolItem xmlns:xsi="http://www.w3.org/2001/XMLSchema-instance" xmlns="http://ns.adobe.com/xfl/2008/" name="FlashAICB_0/Layer 1/&lt;Path&gt;_6" itemID="54cd1fc0-00000583" lastModified="1422729152">
  <timeline>
    <DOMTimeline name="&lt;Path&gt;_6">
      <layers>
        <DOMLayer name="Layer 1" color="#4FFF4F" current="true" isSelected="true">
          <frames>
            <DOMFrame index="0" keyMode="9728">
              <elements>
                <DOMShape selected="true" isDrawingObject="true">
                  <fills>
                    <FillStyle index="1">
                      <SolidColor color="#E5E5D4"/>
                    </FillStyle>
                  </fills>
                  <edges>
                    <Edge fillStyle1="1" edges="!16146 6672[16229 6922 16363 6822!16363 6822[16430 6772 16480 6672!16480 6672|16480 8674!16480 8674|16336 11034!16336 11034|14745 13788!14745 13788|13038 15187!13038 15187[12326 15327 11574 15483!11574 15483[10069 15796 9866 15879!9866
 15879[9757 15924 9098 15844!9098 15844[8685 15794 7709 15646!7709 15646[6700 15493 6339 15448!6339 15448[5702 15368 5628 15412!5628 15412[5480 15501 3490 14361!3490 14361[2750 13938 2115 13548!2115 13548[1494 13168 1468 13124!1468 13124
[1435 13069 1210 12605!1210 12605[949 12066 709 11548!709 11548[0 10020 0 9808!0 9808|0 5411!0 5411|288 3515!288 3515|2148 1551!2148 1551|4664 0!4664 0|4951 0!4951 0|3548 2139!3548 2139[3168 3039 2803 3964!2803 3964[2072 5813 2148 5938
!2148 5938[2286 6166 2715 6948!2715 6948[3203 7836 3282 8036!3282 8036[3352 8212 4017 8644!4017 8644[4194 8759 4544 8982!4544 8982[4829 9169 4951 9274!4951 9274[5204 9493 5943 9782!5943 9782[6424 9971 7056 10169!7056 10169[7400 10277
 8667 10310!8667 10310[9301 10327 9866 10322!9866 10322|12343 9608!12343 9608|13116 9416!13116 9416[13936 9199 14170 9074!14170 9074[14404 8949 15099 7983!15099 7983[15446 7500 15746 7042!15746 7042[15763 6994 15790 6928!15790 6928[15844
 6796 15896 6707!15896 6707[16063 6422 16146 6672"/>
                    <Edge cubics="!4951 0(;4951,0 3548,2139 3548,2139q4951 0 3548 2139);"/>
                    <Edge cubics="!3548 2139(;3548,2139 2027,5738 2148,5938q3548 2139Q3168 3039q2803 3964Q2072 5813q2148 5938);"/>
                    <Edge cubics="!2148 5938(;2269,6138 3161,7731 3282,8036q2148 5938Q2286 6166q2715 6948Q3203 7836q3282 8036);"/>
                    <Edge cubics="!3282 8036(;3403,8340 4565,8940 4951,9274q3282 8036Q3352 8212q4017 8644Q4194 8759q4544 8982Q4829 9169q4951 9274);"/>
                    <Edge cubics="!4951 9274(;5338,9608 6507,9997 7056,10169q4951 9274Q5204 9493q5943 9782Q6424 9971q7056 10169);"/>
                    <Edge cubics="!7056 10169(;7606,10342 9866,10322 9866,10322q7056 10169Q7400 10277q8667 10310Q9301 10327q9866 10322);"/>
                    <Edge cubics="!9866 10322(;9866,10322 12343,9608 12343,9608q9866 10322 12343 9608);"/>
                    <Edge cubics="!12343 9608(;12343,9608 13795,9274 14170,9074q12343 9608Q12343 9608q13116 9416Q13936 9199q14170 9074);"/>
                    <Edge cubics="!14170 9074(;14545,8874 15746,7042 15746,7042q14170 9074Q14404 8949q15099 7983Q15446 7500q15746 7042);"/>
                    <Edge cubics="!15746 7042(;15746,7042 16013,6272 16146,6672q15746 7042Q15763 6994q15790 6928Q15844 6796q15896 6707Q16063 6422q16146 6672);"/>
                    <Edge cubics="!16146 6672(;16279,7072 16480,6672 16480,6672q16146 6672Q16229 6922q16363 6822Q16430 6772q16480 6672);"/>
                    <Edge cubics="!16480 6672(;16480,6672 16480,8674 16480,8674q16480 6672 16480 8674);"/>
                    <Edge cubics="!16480 8674(;16480,8674 16336,11034 16336,11034q16480 8674 16336 11034);"/>
                    <Edge cubics="!16336 11034(;16336,11034 14745,13788 14745,13788q16336 11034 14745 13788);"/>
                    <Edge cubics="!14745 13788(;14745,13788 13038,15187 13038,15187q14745 13788 13038 15187);"/>
                    <Edge cubics="!13038 15187(;13038,15187 10191,15746 9866,15879q13038 15187Q12326 15327q11574 15483Q10069 15796q9866 15879);"/>
                    <Edge cubics="!9866 15879(;9541,16013 5851,15279 5628,15412q9866 15879Q9757 15924q9098 15844Q8685 15794q7709 15646Q6700 15493q6339 15448Q5702 15368q5628 15412);"/>
                    <Edge cubics="!5628 15412(;5405,15546 1535,13238 1468,13124q5628 15412Q5480 15501q3490 14361Q2750 13938q2115 13548Q1494 13168q1468 13124);"/>
                    <Edge cubics="!1468 13124(;1401,13010 0,10141 0,9808q1468 13124Q1435 13069q1210 12605Q949 12066q709 11548Q0 10020q0 9808);"/>
                    <Edge cubics="!0 9808(;0,9474 0,5411 0,5411q0 9808 0 5411);"/>
                    <Edge cubics="!0 5411(;0,5411 288,3515 288,3515q0 5411 288 3515);"/>
                    <Edge cubics="!288 3515(;288,3515 2148,1551 2148,1551q288 3515 2148 1551);"/>
                    <Edge cubics="!2148 1551(;2148,1551 4664,0 4664,0q2148 1551 4664 0);"/>
                    <Edge cubics="!4664 0(;4807,0 4807,0 4951,0q4664 0 4951 0);"/>
                  </edges>
                </DOMShape>
              </elements>
            </DOMFrame>
          </frames>
        </DOMLayer>
      </layers>
    </DOMTimeline>
  </timeline>
</DOMSymbolItem>